xumx/__init__.py
xumx/args.py
xumx/comm.py
xumx/data.py
xumx/eval.py
xumx/loss.py
xumx/lr_scheduler.py
xumx/model.py
xumx/test.py
xumx/train.py
xumx/utils.py
xumx_unofficial-0.2.0.dist-info/LICENSE
xumx_unofficial-0.2.0.dist-info/METADATA
xumx_unofficial-0.2.0.dist-info/WHEEL
xumx_unofficial-0.2.0.dist-info/top_level.txt
xumx_unofficial-0.2.0.dist-info/RECORD
