Metadata-Version: 2.1
Name: xumx-unofficial
Version: 0.2.0
Summary: Unofficial NNabla implementation of CrossNet-Open-Unmix (X-UMX), originally created by Sony Research AI.
Home-page: https://github.com/JeffreyCA/xumx
Author: JeffreyCA
Author-email: jeffreyca16@gmail.com
License: UNKNOWN
Platform: UNKNOWN
Classifier: Programming Language :: Python :: 3
Classifier: License :: OSI Approved :: Apache Software License
Classifier: Operating System :: OS Independent
Requires-Python: >=3.6
License-File: LICENSE
Requires-Dist: lameenc (>=1.2.2)
Requires-Dist: musdb (>=0.3.1)
Requires-Dist: museval (>=0.3.0)
Requires-Dist: requests (>=2.22)
Requires-Dist: scipy (>=1.3.1)
Requires-Dist: setuptools (>=41.0.0)
Requires-Dist: norbert (>=0.2.1)
Requires-Dist: resampy (>=0.2.2)
Requires-Dist: nnabla (>=1.13.0)
Requires-Dist: pydub (>=0.24.1)
